<stg><name>KeccakWidth1600_Spon</name>


<trans_list>

<trans id="135" from="1" to="2">
<condition id="-1">
<or_exp><and_exp><literal name="icmp_ln297" val="1"/>
</and_exp></or_exp>
</condition>
</trans>

<trans id="136" from="1" to="6">
<condition id="-1">
<or_exp><and_exp><literal name="icmp_ln297" val="0"/>
</and_exp></or_exp>
</condition>
</trans>

<trans id="138" from="2" to="3">
<condition id="-1">
<or_exp><and_exp></and_exp></or_exp>
</condition>
</trans>

<trans id="139" from="3" to="4">
<condition id="-1">
<or_exp><and_exp></and_exp></or_exp>
</condition>
</trans>

<trans id="140" from="4" to="5">
<condition id="-1">
<or_exp><and_exp></and_exp></or_exp>
</condition>
</trans>

<trans id="141" from="5" to="6">
<condition id="-1">
<or_exp><and_exp></and_exp></or_exp>
</condition>
</trans>

<trans id="142" from="6" to="7">
<condition id="-1">
<or_exp><and_exp></and_exp></or_exp>
</condition>
</trans>

<trans id="143" from="7" to="12">
<condition id="-1">
<or_exp><and_exp><literal name="icmp_ln302" val="1"/>
<literal name="icmp_ln303_1" val="1"/>
</and_exp><and_exp><literal name="icmp_ln302" val="1"/>
<literal name="icmp_ln303" val="0"/>
</and_exp></or_exp>
</condition>
</trans>

<trans id="145" from="7" to="8">
<condition id="-1">
<or_exp><and_exp><literal name="icmp_ln302" val="1"/>
<literal name="icmp_ln303" val="1"/>
<literal name="icmp_ln303_1" val="0"/>
</and_exp></or_exp>
</condition>
</trans>

<trans id="146" from="8" to="9">
<condition id="-1">
<or_exp><and_exp><literal name="icmp_ln304" val="0"/>
</and_exp></or_exp>
</condition>
</trans>

<trans id="153" from="8" to="16">
<condition id="-1">
<or_exp><and_exp><literal name="icmp_ln304" val="1"/>
</and_exp></or_exp>
</condition>
</trans>

<trans id="148" from="9" to="10">
<condition id="-1">
<or_exp><and_exp></and_exp></or_exp>
</condition>
</trans>

<trans id="149" from="10" to="11">
<condition id="-1">
<or_exp><and_exp><literal name="icmp_ln393_1" val="0"/>
</and_exp></or_exp>
</condition>
</trans>

<trans id="152" from="10" to="8">
<condition id="-1">
<or_exp><and_exp><literal name="icmp_ln393_1" val="1"/>
</and_exp></or_exp>
</condition>
</trans>

<trans id="151" from="11" to="10">
<condition id="-1">
<or_exp><and_exp></and_exp></or_exp>
</condition>
</trans>

<trans id="155" from="12" to="13">
<condition id="-1">
<or_exp><and_exp></and_exp></or_exp>
</condition>
</trans>

<trans id="157" from="13" to="14">
<condition id="-1">
<or_exp><and_exp></and_exp></or_exp>
</condition>
</trans>

<trans id="158" from="14" to="15">
<condition id="-1">
<or_exp><and_exp><literal name="icmp_ln393" val="0"/>
</and_exp></or_exp>
</condition>
</trans>

<trans id="161" from="14" to="16">
<condition id="-1">
<or_exp><and_exp><literal name="icmp_ln393" val="1"/>
</and_exp></or_exp>
</condition>
</trans>

<trans id="160" from="15" to="14">
<condition id="-1">
<or_exp><and_exp></and_exp></or_exp>
</condition>
</trans>

<trans id="162" from="16" to="7">
<condition id="-1">
<or_exp><and_exp></and_exp></or_exp>
</condition>
</trans>
</trans_list>



<state_list>

<state id="1" st_id="1">

<operation id="17" st_id="1" stage="1" lat="1">
<core>NULL</core>
<MemPortIdVec></MemPortIdVec>
<condition id="-1">
<or_exp><and_exp></and_exp></or_exp>
</condition>

<Node id="11" bw="8" op_0_bw="8" op_1_bw="8">
<![CDATA[
:0  %dataByteLen_read = call i8 @_ssdm_op_Read.ap_auto.i8(i8 %dataByteLen)

]]></Node>
<StgValue><ssdm name="dataByteLen_read"/></StgValue>
</operation>

<operation id="18" st_id="1" stage="1" lat="1">
<core>NULL</core>
<MemPortIdVec></MemPortIdVec>
<condition id="-1">
<or_exp><and_exp></and_exp></or_exp>
</condition>

<Node id="12" bw="1" op_0_bw="1" op_1_bw="1">
<![CDATA[
:1  %data_offset1_read = call i1 @_ssdm_op_Read.ap_auto.i1(i1 %data_offset1)

]]></Node>
<StgValue><ssdm name="data_offset1_read"/></StgValue>
</operation>

<operation id="19" st_id="1" stage="1" lat="1">
<core>NULL</core>
<MemPortIdVec></MemPortIdVec>
<condition id="-1">
<or_exp><and_exp></and_exp></or_exp>
</condition>

<Node id="13" bw="32" op_0_bw="32" op_1_bw="32">
<![CDATA[
:2  %instance_squeezing_r = call i32 @_ssdm_op_Read.ap_auto.i32(i32 %instance_squeezing_read)

]]></Node>
<StgValue><ssdm name="instance_squeezing_r"/></StgValue>
</operation>

<operation id="20" st_id="1" stage="1" lat="1">
<core>NULL</core>
<MemPortIdVec></MemPortIdVec>
<condition id="-1">
<or_exp><and_exp></and_exp></or_exp>
</condition>

<Node id="14" bw="32" op_0_bw="32" op_1_bw="32">
<![CDATA[
:3  %instance_byteIOIndex_68 = call i32 @_ssdm_op_Read.ap_auto.i32(i32 %instance_byteIOIndex_read)

]]></Node>
<StgValue><ssdm name="instance_byteIOIndex_68"/></StgValue>
</operation>

<operation id="21" st_id="1" stage="1" lat="1">
<core>NULL</core>
<MemPortIdVec></MemPortIdVec>
<condition id="-1">
<or_exp><and_exp></and_exp></or_exp>
</condition>

<Node id="15" bw="9" op_0_bw="8">
<![CDATA[
:4  %dataByteLen_cast = sext i8 %dataByteLen_read to i9

]]></Node>
<StgValue><ssdm name="dataByteLen_cast"/></StgValue>
</operation>

<operation id="22" st_id="1" stage="1" lat="1">
<core>NULL</core>
<MemPortIdVec></MemPortIdVec>
<condition id="-1">
<or_exp><and_exp></and_exp></or_exp>
</condition>

<Node id="16" bw="34" op_0_bw="9">
<![CDATA[
:5  %zext_ln394_13 = zext i9 %dataByteLen_cast to i34

]]></Node>
<StgValue><ssdm name="zext_ln394_13"/></StgValue>
</operation>

<operation id="23" st_id="1" stage="1" lat="1">
<core>Sel</core>
<MemPortIdVec></MemPortIdVec>
<condition id="-1">
<or_exp><and_exp></and_exp></or_exp>
</condition>

<Node id="17" bw="10" op_0_bw="1" op_1_bw="10" op_2_bw="10">
<![CDATA[
:6  %select_ln394 = select i1 %data_offset1_read, i10 166, i10 0

]]></Node>
<StgValue><ssdm name="select_ln394"/></StgValue>
</operation>

<operation id="24" st_id="1" stage="1" lat="1">
<core>Cmp</core>
<MemPortIdVec></MemPortIdVec>
<condition id="-1">
<or_exp><and_exp></and_exp></or_exp>
</condition>

<Node id="18" bw="1" op_0_bw="32" op_1_bw="32">
<![CDATA[
:7  %icmp_ln297 = icmp eq i32 %instance_squeezing_r, 0

]]></Node>
<StgValue><ssdm name="icmp_ln297"/></StgValue>
</operation>

<operation id="25" st_id="1" stage="1" lat="1">
<core>NULL</core>
<MemPortIdVec></MemPortIdVec>
<condition id="-1">
<or_exp><and_exp></and_exp></or_exp>
</condition>

<Node id="19" bw="0" op_0_bw="1" op_1_bw="0" op_2_bw="0">
<![CDATA[
:8  br i1 %icmp_ln297, label %1, label %._crit_edge

]]></Node>
<StgValue><ssdm name="br_ln297"/></StgValue>
</operation>

<operation id="26" st_id="1" stage="1" lat="1">
<core>NULL</core>
<MemPortIdVec></MemPortIdVec>
<condition id="-1">
<or_exp><and_exp><literal name="icmp_ln297" val="1"/>
</and_exp></or_exp>
</condition>

<Node id="21" bw="64" op_0_bw="32">
<![CDATA[
:0  %zext_ln149 = zext i32 %instance_byteIOIndex_68 to i64

]]></Node>
<StgValue><ssdm name="zext_ln149"/></StgValue>
</operation>

<operation id="27" st_id="1" stage="1" lat="1">
<core>NULL</core>
<MemPortIdVec></MemPortIdVec>
<condition id="-1">
<or_exp><and_exp><literal name="icmp_ln297" val="1"/>
</and_exp></or_exp>
</condition>

<Node id="22" bw="8" op_0_bw="8" op_1_bw="64" op_2_bw="64">
<![CDATA[
:1  %instance_state_addr = getelementptr [200 x i8]* %instance_state, i64 0, i64 %zext_ln149

]]></Node>
<StgValue><ssdm name="instance_state_addr"/></StgValue>
</operation>

<operation id="28" st_id="1" stage="2" lat="2">
<core>RAM</core>
<MemPortIdVec>0 </MemPortIdVec>
<condition id="-1">
<or_exp><and_exp><literal name="icmp_ln297" val="1"/>
</and_exp></or_exp>
</condition>

<Node id="23" bw="8" op_0_bw="8">
<![CDATA[
:2  %instance_state_load = load i8* %instance_state_addr, align 1

]]></Node>
<StgValue><ssdm name="instance_state_load"/></StgValue>
</operation>
</state>

<state id="2" st_id="2">

<operation id="29" st_id="2" stage="1" lat="2">
<core>RAM</core>
<MemPortIdVec>0 </MemPortIdVec>
<condition id="-1">
<or_exp><and_exp></and_exp></or_exp>
</condition>

<Node id="23" bw="8" op_0_bw="8">
<![CDATA[
:2  %instance_state_load = load i8* %instance_state_addr, align 1

]]></Node>
<StgValue><ssdm name="instance_state_load"/></StgValue>
</operation>

<operation id="30" st_id="2" stage="1" lat="1">
<core>LogicGate</core>
<MemPortIdVec></MemPortIdVec>
<condition id="-1">
<or_exp><and_exp></and_exp></or_exp>
</condition>

<Node id="24" bw="8" op_0_bw="8" op_1_bw="8">
<![CDATA[
:3  %xor_ln149 = xor i8 %instance_state_load, 1

]]></Node>
<StgValue><ssdm name="xor_ln149"/></StgValue>
</operation>

<operation id="31" st_id="2" stage="1" lat="1">
<core>RAM</core>
<MemPortIdVec>0 </MemPortIdVec>
<condition id="-1">
<or_exp><and_exp></and_exp></or_exp>
</condition>

<Node id="25" bw="0" op_0_bw="8" op_1_bw="8" op_2_bw="8">
<![CDATA[
:4  store i8 %xor_ln149, i8* %instance_state_addr, align 1

]]></Node>
<StgValue><ssdm name="store_ln149"/></StgValue>
</operation>
</state>

<state id="3" st_id="3">

<operation id="32" st_id="3" stage="1" lat="1">
<core>NULL</core>
<MemPortIdVec></MemPortIdVec>
<condition id="-1">
<or_exp><and_exp></and_exp></or_exp>
</condition>

<Node id="26" bw="8" op_0_bw="8" op_1_bw="64" op_2_bw="64">
<![CDATA[
:5  %instance_state_addr_1 = getelementptr [200 x i8]* %instance_state, i64 0, i64 167

]]></Node>
<StgValue><ssdm name="instance_state_addr_1"/></StgValue>
</operation>

<operation id="33" st_id="3" stage="2" lat="2">
<core>RAM</core>
<MemPortIdVec>0 </MemPortIdVec>
<condition id="-1">
<or_exp><and_exp></and_exp></or_exp>
</condition>

<Node id="27" bw="8" op_0_bw="8" op_1_bw="0">
<![CDATA[
:6  %instance_state_load_1 = load i8* %instance_state_addr_1, align 1

]]></Node>
<StgValue><ssdm name="instance_state_load_1"/></StgValue>
</operation>
</state>

<state id="4" st_id="4">

<operation id="34" st_id="4" stage="1" lat="2">
<core>RAM</core>
<MemPortIdVec>0 </MemPortIdVec>
<condition id="-1">
<or_exp><and_exp></and_exp></or_exp>
</condition>

<Node id="27" bw="8" op_0_bw="8" op_1_bw="0">
<![CDATA[
:6  %instance_state_load_1 = load i8* %instance_state_addr_1, align 1

]]></Node>
<StgValue><ssdm name="instance_state_load_1"/></StgValue>
</operation>

<operation id="35" st_id="4" stage="1" lat="1">
<core>LogicGate</core>
<MemPortIdVec></MemPortIdVec>
<condition id="-1">
<or_exp><and_exp></and_exp></or_exp>
</condition>

<Node id="28" bw="8" op_0_bw="8" op_1_bw="8">
<![CDATA[
:7  %xor_ln149_1 = xor i8 %instance_state_load_1, -128

]]></Node>
<StgValue><ssdm name="xor_ln149_1"/></StgValue>
</operation>

<operation id="36" st_id="4" stage="1" lat="1">
<core>RAM</core>
<MemPortIdVec>0 </MemPortIdVec>
<condition id="-1">
<or_exp><and_exp></and_exp></or_exp>
</condition>

<Node id="29" bw="0" op_0_bw="8" op_1_bw="8" op_2_bw="8">
<![CDATA[
:8  store i8 %xor_ln149_1, i8* %instance_state_addr_1, align 1

]]></Node>
<StgValue><ssdm name="store_ln149"/></StgValue>
</operation>
</state>

<state id="5" st_id="5">

<operation id="37" st_id="5" stage="2" lat="2">
<core></core>
<MemPortIdVec></MemPortIdVec>
<condition id="-1">
<or_exp><and_exp></and_exp></or_exp>
</condition>

<Node id="30" bw="0" op_0_bw="0" op_1_bw="8" op_2_bw="6" op_3_bw="64" op_4_bw="0">
<![CDATA[
:9  call fastcc void @KeccakP1600_Permute_([200 x i8]* %instance_state)

]]></Node>
<StgValue><ssdm name="call_ln279"/></StgValue>
</operation>
</state>

<state id="6" st_id="6">

<operation id="38" st_id="6" stage="1" lat="2">
<core></core>
<MemPortIdVec></MemPortIdVec>
<condition id="-1">
<or_exp><and_exp><literal name="icmp_ln297" val="1"/>
</and_exp></or_exp>
</condition>

<Node id="30" bw="0" op_0_bw="0" op_1_bw="8" op_2_bw="6" op_3_bw="64" op_4_bw="0">
<![CDATA[
:9  call fastcc void @KeccakP1600_Permute_([200 x i8]* %instance_state)

]]></Node>
<StgValue><ssdm name="call_ln279"/></StgValue>
</operation>

<operation id="39" st_id="6" stage="1" lat="1">
<core>NULL</core>
<MemPortIdVec></MemPortIdVec>
<condition id="-1">
<or_exp><and_exp><literal name="icmp_ln297" val="1"/>
</and_exp></or_exp>
</condition>

<Node id="31" bw="0" op_0_bw="0">
<![CDATA[
:10  br label %._crit_edge

]]></Node>
<StgValue><ssdm name="br_ln298"/></StgValue>
</operation>

<operation id="40" st_id="6" stage="1" lat="1">
<core>NULL</core>
<MemPortIdVec></MemPortIdVec>
<condition id="-1">
<or_exp><and_exp></and_exp></or_exp>
</condition>

<Node id="33" bw="32" op_0_bw="32" op_1_bw="0" op_2_bw="32" op_3_bw="0">
<![CDATA[
._crit_edge:0  %instance_byteIOIndex = phi i32 [ 0, %1 ], [ %instance_byteIOIndex_68, %0 ]

]]></Node>
<StgValue><ssdm name="instance_byteIOIndex"/></StgValue>
</operation>

<operation id="41" st_id="6" stage="1" lat="1">
<core>NULL</core>
<MemPortIdVec></MemPortIdVec>
<condition id="-1">
<or_exp><and_exp></and_exp></or_exp>
</condition>

<Node id="34" bw="34" op_0_bw="32">
<![CDATA[
._crit_edge:1  %i_36 = alloca i34

]]></Node>
<StgValue><ssdm name="i_36"/></StgValue>
</operation>

<operation id="42" st_id="6" stage="1" lat="1">
<core>NULL</core>
<MemPortIdVec></MemPortIdVec>
<condition id="-1">
<or_exp><and_exp></and_exp></or_exp>
</condition>

<Node id="35" bw="30" op_0_bw="9">
<![CDATA[
._crit_edge:2  %zext_ln303 = zext i9 %dataByteLen_cast to i30

]]></Node>
<StgValue><ssdm name="zext_ln303"/></StgValue>
</operation>

<operation id="43" st_id="6" stage="1" lat="1">
<core>NULL</core>
<MemPortIdVec></MemPortIdVec>
<condition id="-1">
<or_exp><and_exp></and_exp></or_exp>
</condition>

<Node id="36" bw="32" op_0_bw="9">
<![CDATA[
._crit_edge:3  %zext_ln320 = zext i9 %dataByteLen_cast to i32

]]></Node>
<StgValue><ssdm name="zext_ln320"/></StgValue>
</operation>

<operation id="44" st_id="6" stage="1" lat="1">
<core>NULL</core>
<MemPortIdVec></MemPortIdVec>
<condition id="-1">
<or_exp><and_exp></and_exp></or_exp>
</condition>

<Node id="37" bw="0" op_0_bw="34" op_1_bw="34">
<![CDATA[
._crit_edge:4  store i34 0, i34* %i_36

]]></Node>
<StgValue><ssdm name="store_ln302"/></StgValue>
</operation>

<operation id="45" st_id="6" stage="1" lat="1">
<core>NULL</core>
<MemPortIdVec></MemPortIdVec>
<condition id="-1">
<or_exp><and_exp></and_exp></or_exp>
</condition>

<Node id="38" bw="0" op_0_bw="0">
<![CDATA[
._crit_edge:5  br label %.backedge

]]></Node>
<StgValue><ssdm name="br_ln302"/></StgValue>
</operation>
</state>

<state id="7" st_id="7">

<operation id="46" st_id="7" stage="1" lat="1">
<core>NULL</core>
<MemPortIdVec></MemPortIdVec>
<condition id="-1">
<or_exp><and_exp></and_exp></or_exp>
</condition>

<Node id="40" bw="32" op_0_bw="32" op_1_bw="0" op_2_bw="32" op_3_bw="0">
<![CDATA[
.backedge:0  %instance_byteIOIndex_1 = phi i32 [ %instance_byteIOIndex, %._crit_edge ], [ %instance_byteIOIndex_3, %.backedge.backedge ]

]]></Node>
<StgValue><ssdm name="instance_byteIOIndex_1"/></StgValue>
</operation>

<operation id="47" st_id="7" stage="1" lat="1">
<core>NULL</core>
<MemPortIdVec></MemPortIdVec>
<condition id="-1">
<or_exp><and_exp></and_exp></or_exp>
</condition>

<Node id="41" bw="64" op_0_bw="64" op_1_bw="0" op_2_bw="64" op_3_bw="0">
<![CDATA[
.backedge:1  %curData_0_idx = phi i64 [ 0, %._crit_edge ], [ %add_ln329, %.backedge.backedge ]

]]></Node>
<StgValue><ssdm name="curData_0_idx"/></StgValue>
</operation>

<operation id="48" st_id="7" stage="1" lat="1">
<core>NULL</core>
<MemPortIdVec></MemPortIdVec>
<condition id="-1">
<or_exp><and_exp></and_exp></or_exp>
</condition>

<Node id="42" bw="34" op_0_bw="34" op_1_bw="0">
<![CDATA[
.backedge:2  %i_36_load = load i34* %i_36

]]></Node>
<StgValue><ssdm name="i_36_load"/></StgValue>
</operation>

<operation id="49" st_id="7" stage="1" lat="1">
<core>Cmp</core>
<MemPortIdVec></MemPortIdVec>
<condition id="-1">
<or_exp><and_exp></and_exp></or_exp>
</condition>

<Node id="43" bw="1" op_0_bw="34" op_1_bw="34">
<![CDATA[
.backedge:3  %icmp_ln302 = icmp ult i34 %i_36_load, %zext_ln394_13

]]></Node>
<StgValue><ssdm name="icmp_ln302"/></StgValue>
</operation>

<operation id="50" st_id="7" stage="1" lat="1">
<core>NULL</core>
<MemPortIdVec></MemPortIdVec>
<condition id="-1">
<or_exp><and_exp></and_exp></or_exp>
</condition>

<Node id="44" bw="0" op_0_bw="1" op_1_bw="0" op_2_bw="0">
<![CDATA[
.backedge:4  br i1 %icmp_ln302, label %2, label %10

]]></Node>
<StgValue><ssdm name="br_ln302"/></StgValue>
</operation>

<operation id="51" st_id="7" stage="1" lat="1">
<core>Cmp</core>
<MemPortIdVec></MemPortIdVec>
<condition id="-1">
<or_exp><and_exp><literal name="icmp_ln302" val="1"/>
</and_exp></or_exp>
</condition>

<Node id="46" bw="1" op_0_bw="32" op_1_bw="32">
<![CDATA[
:0  %icmp_ln303 = icmp eq i32 %instance_byteIOIndex_1, 168

]]></Node>
<StgValue><ssdm name="icmp_ln303"/></StgValue>
</operation>

<operation id="52" st_id="7" stage="1" lat="1">
<core>NULL</core>
<MemPortIdVec></MemPortIdVec>
<condition id="-1">
<or_exp><and_exp><literal name="icmp_ln302" val="1"/>
</and_exp></or_exp>
</condition>

<Node id="47" bw="0" op_0_bw="1" op_1_bw="0" op_2_bw="0">
<![CDATA[
:1  br i1 %icmp_ln303, label %3, label %._crit_edge3.critedge

]]></Node>
<StgValue><ssdm name="br_ln303"/></StgValue>
</operation>

<operation id="53" st_id="7" stage="1" lat="1">
<core>NULL</core>
<MemPortIdVec></MemPortIdVec>
<condition id="-1">
<or_exp><and_exp><literal name="icmp_ln302" val="1"/>
<literal name="icmp_ln303" val="1"/>
</and_exp></or_exp>
</condition>

<Node id="49" bw="30" op_0_bw="34">
<![CDATA[
:0  %trunc_ln303 = trunc i34 %i_36_load to i30

]]></Node>
<StgValue><ssdm name="trunc_ln303"/></StgValue>
</operation>

<operation id="54" st_id="7" stage="1" lat="1">
<core>AddSub</core>
<MemPortIdVec></MemPortIdVec>
<condition id="-1">
<or_exp><and_exp><literal name="icmp_ln302" val="1"/>
<literal name="icmp_ln303" val="1"/>
</and_exp></or_exp>
</condition>

<Node id="50" bw="30" op_0_bw="30" op_1_bw="30">
<![CDATA[
:1  %add_ln303 = add i30 168, %trunc_ln303

]]></Node>
<StgValue><ssdm name="add_ln303"/></StgValue>
</operation>

<operation id="55" st_id="7" stage="1" lat="1">
<core>Cmp</core>
<MemPortIdVec></MemPortIdVec>
<condition id="-1">
<or_exp><and_exp><literal name="icmp_ln302" val="1"/>
<literal name="icmp_ln303" val="1"/>
</and_exp></or_exp>
</condition>

<Node id="51" bw="1" op_0_bw="30" op_1_bw="30">
<![CDATA[
:2  %icmp_ln303_1 = icmp ugt i30 %add_ln303, %zext_ln303

]]></Node>
<StgValue><ssdm name="icmp_ln303_1"/></StgValue>
</operation>

<operation id="56" st_id="7" stage="1" lat="1">
<core>NULL</core>
<MemPortIdVec></MemPortIdVec>
<condition id="-1">
<or_exp><and_exp><literal name="icmp_ln302" val="1"/>
<literal name="icmp_ln303" val="1"/>
</and_exp></or_exp>
</condition>

<Node id="52" bw="0" op_0_bw="1" op_1_bw="0" op_2_bw="0">
<![CDATA[
:3  br i1 %icmp_ln303_1, label %._crit_edge1, label %4

]]></Node>
<StgValue><ssdm name="br_ln303"/></StgValue>
</operation>

<operation id="57" st_id="7" stage="1" lat="1">
<core>AddSub</core>
<MemPortIdVec></MemPortIdVec>
<condition id="-1">
<or_exp><and_exp><literal name="icmp_ln302" val="1"/>
<literal name="icmp_ln303" val="1"/>
<literal name="icmp_ln303_1" val="0"/>
</and_exp></or_exp>
</condition>

<Node id="54" bw="34" op_0_bw="34" op_1_bw="34">
<![CDATA[
:0  %j = sub i34 %zext_ln394_13, %i_36_load

]]></Node>
<StgValue><ssdm name="j"/></StgValue>
</operation>

<operation id="58" st_id="7" stage="1" lat="1">
<core>NULL</core>
<MemPortIdVec></MemPortIdVec>
<condition id="-1">
<or_exp><and_exp><literal name="icmp_ln302" val="1"/>
<literal name="icmp_ln303" val="1"/>
<literal name="icmp_ln303_1" val="0"/>
</and_exp></or_exp>
</condition>

<Node id="55" bw="64" op_0_bw="34">
<![CDATA[
:1  %sext_ln304 = sext i34 %j to i64

]]></Node>
<StgValue><ssdm name="sext_ln304"/></StgValue>
</operation>

<operation id="59" st_id="7" stage="1" lat="1">
<core>NULL</core>
<MemPortIdVec></MemPortIdVec>
<condition id="-1">
<or_exp><and_exp><literal name="icmp_ln302" val="1"/>
<literal name="icmp_ln303" val="1"/>
<literal name="icmp_ln303_1" val="0"/>
</and_exp></or_exp>
</condition>

<Node id="56" bw="0" op_0_bw="0">
<![CDATA[
:2  br label %5

]]></Node>
<StgValue><ssdm name="br_ln304"/></StgValue>
</operation>

<operation id="60" st_id="7" stage="2" lat="2">
<core></core>
<MemPortIdVec></MemPortIdVec>
<condition id="-1">
<or_exp><and_exp><literal name="icmp_ln302" val="1"/>
<literal name="icmp_ln303" val="1"/>
<literal name="icmp_ln303_1" val="1"/>
</and_exp></or_exp>
</condition>

<Node id="97" bw="0" op_0_bw="0" op_1_bw="8" op_2_bw="6" op_3_bw="64" op_4_bw="0">
<![CDATA[
._crit_edge1:0  call fastcc void @KeccakP1600_Permute_([200 x i8]* %instance_state)

]]></Node>
<StgValue><ssdm name="call_ln317"/></StgValue>
</operation>

<operation id="61" st_id="7" stage="1" lat="1">
<core>NULL</core>
<MemPortIdVec></MemPortIdVec>
<condition id="-1">
<or_exp><and_exp><literal name="icmp_ln302" val="0"/>
</and_exp></or_exp>
</condition>

<Node id="140" bw="0">
<![CDATA[
:0  ret void

]]></Node>
<StgValue><ssdm name="ret_ln0"/></StgValue>
</operation>
</state>

<state id="8" st_id="8">

<operation id="62" st_id="8" stage="1" lat="1">
<core>NULL</core>
<MemPortIdVec></MemPortIdVec>
<condition id="-1">
<or_exp><and_exp></and_exp></or_exp>
</condition>

<Node id="58" bw="64" op_0_bw="64" op_1_bw="0" op_2_bw="64" op_3_bw="0">
<![CDATA[
:0  %j_0 = phi i64 [ %sext_ln304, %4 ], [ %j_18, %KeccakP1600_ExtractBytes.exit ]

]]></Node>
<StgValue><ssdm name="j_0"/></StgValue>
</operation>

<operation id="63" st_id="8" stage="1" lat="1">
<core>NULL</core>
<MemPortIdVec></MemPortIdVec>
<condition id="-1">
<or_exp><and_exp></and_exp></or_exp>
</condition>

<Node id="59" bw="64" op_0_bw="64" op_1_bw="0" op_2_bw="64" op_3_bw="0">
<![CDATA[
:1  %curData_1_rec = phi i64 [ 0, %4 ], [ %add_ln310, %KeccakP1600_ExtractBytes.exit ]

]]></Node>
<StgValue><ssdm name="curData_1_rec"/></StgValue>
</operation>

<operation id="64" st_id="8" stage="1" lat="1">
<core>Cmp</core>
<MemPortIdVec></MemPortIdVec>
<condition id="-1">
<or_exp><and_exp></and_exp></or_exp>
</condition>

<Node id="60" bw="1" op_0_bw="64" op_1_bw="64">
<![CDATA[
:2  %icmp_ln304 = icmp ult i64 %j_0, 168

]]></Node>
<StgValue><ssdm name="icmp_ln304"/></StgValue>
</operation>

<operation id="65" st_id="8" stage="1" lat="1">
<core>NULL</core>
<MemPortIdVec></MemPortIdVec>
<condition id="-1">
<or_exp><and_exp></and_exp></or_exp>
</condition>

<Node id="61" bw="0" op_0_bw="1" op_1_bw="0" op_2_bw="0">
<![CDATA[
:3  br i1 %icmp_ln304, label %8, label %6

]]></Node>
<StgValue><ssdm name="br_ln304"/></StgValue>
</operation>

<operation id="66" st_id="8" stage="2" lat="2">
<core></core>
<MemPortIdVec></MemPortIdVec>
<condition id="-1">
<or_exp><and_exp><literal name="icmp_ln304" val="0"/>
</and_exp></or_exp>
</condition>

<Node id="63" bw="0" op_0_bw="0" op_1_bw="8" op_2_bw="6" op_3_bw="64" op_4_bw="0">
<![CDATA[
:0  call fastcc void @KeccakP1600_Permute_([200 x i8]* %instance_state)

]]></Node>
<StgValue><ssdm name="call_ln305"/></StgValue>
</operation>

<operation id="67" st_id="8" stage="1" lat="1">
<core>NULL</core>
<MemPortIdVec></MemPortIdVec>
<condition id="-1">
<or_exp><and_exp><literal name="icmp_ln304" val="1"/>
</and_exp></or_exp>
</condition>

<Node id="91" bw="34" op_0_bw="9">
<![CDATA[
:0  %zext_ln312 = zext i9 %dataByteLen_cast to i34

]]></Node>
<StgValue><ssdm name="zext_ln312"/></StgValue>
</operation>

<operation id="68" st_id="8" stage="1" lat="1">
<core>NULL</core>
<MemPortIdVec></MemPortIdVec>
<condition id="-1">
<or_exp><and_exp><literal name="icmp_ln304" val="1"/>
</and_exp></or_exp>
</condition>

<Node id="92" bw="34" op_0_bw="64">
<![CDATA[
:1  %trunc_ln312 = trunc i64 %j_0 to i34

]]></Node>
<StgValue><ssdm name="trunc_ln312"/></StgValue>
</operation>

<operation id="69" st_id="8" stage="1" lat="1">
<core>AddSub</core>
<MemPortIdVec></MemPortIdVec>
<condition id="-1">
<or_exp><and_exp><literal name="icmp_ln304" val="1"/>
</and_exp></or_exp>
</condition>

<Node id="93" bw="34" op_0_bw="34" op_1_bw="34">
<![CDATA[
:2  %sub_ln312 = sub i34 %zext_ln312, %trunc_ln312

]]></Node>
<StgValue><ssdm name="sub_ln312"/></StgValue>
</operation>

<operation id="70" st_id="8" stage="1" lat="1">
<core>NULL</core>
<MemPortIdVec></MemPortIdVec>
<condition id="-1">
<or_exp><and_exp><literal name="icmp_ln304" val="1"/>
</and_exp></or_exp>
</condition>

<Node id="94" bw="0" op_0_bw="34" op_1_bw="34" op_2_bw="0" op_3_bw="34">
<![CDATA[
:3  store i34 %sub_ln312, i34* %i_36

]]></Node>
<StgValue><ssdm name="store_ln313"/></StgValue>
</operation>

<operation id="71" st_id="8" stage="1" lat="1">
<core>NULL</core>
<MemPortIdVec></MemPortIdVec>
<condition id="-1">
<or_exp><and_exp><literal name="icmp_ln304" val="1"/>
</and_exp></or_exp>
</condition>

<Node id="95" bw="0" op_0_bw="0">
<![CDATA[
:4  br label %.backedge.backedge

]]></Node>
<StgValue><ssdm name="br_ln313"/></StgValue>
</operation>
</state>

<state id="9" st_id="9">

<operation id="72" st_id="9" stage="1" lat="2">
<core></core>
<MemPortIdVec></MemPortIdVec>
<condition id="-1">
<or_exp><and_exp></and_exp></or_exp>
</condition>

<Node id="63" bw="0" op_0_bw="0" op_1_bw="8" op_2_bw="6" op_3_bw="64" op_4_bw="0">
<![CDATA[
:0  call fastcc void @KeccakP1600_Permute_([200 x i8]* %instance_state)

]]></Node>
<StgValue><ssdm name="call_ln305"/></StgValue>
</operation>

<operation id="73" st_id="9" stage="1" lat="1">
<core>NULL</core>
<MemPortIdVec></MemPortIdVec>
<condition id="-1">
<or_exp><and_exp></and_exp></or_exp>
</condition>

<Node id="64" bw="0" op_0_bw="0">
<![CDATA[
:1  br label %._crit_edge1.i

]]></Node>
<StgValue><ssdm name="br_ln390"/></StgValue>
</operation>
</state>

<state id="10" st_id="10">

<operation id="74" st_id="10" stage="1" lat="1">
<core>NULL</core>
<MemPortIdVec></MemPortIdVec>
<condition id="-1">
<or_exp><and_exp></and_exp></or_exp>
</condition>

<Node id="66" bw="8" op_0_bw="8" op_1_bw="0" op_2_bw="8" op_3_bw="0">
<![CDATA[
._crit_edge1.i:0  %loop_0_i = phi i8 [ %loop_53, %7 ], [ 0, %6 ]

]]></Node>
<StgValue><ssdm name="loop_0_i"/></StgValue>
</operation>

<operation id="75" st_id="10" stage="1" lat="1">
<core>Cmp</core>
<MemPortIdVec></MemPortIdVec>
<condition id="-1">
<or_exp><and_exp></and_exp></or_exp>
</condition>

<Node id="67" bw="1" op_0_bw="8" op_1_bw="8">
<![CDATA[
._crit_edge1.i:1  %icmp_ln393_1 = icmp eq i8 %loop_0_i, -88

]]></Node>
<StgValue><ssdm name="icmp_ln393_1"/></StgValue>
</operation>

<operation id="76" st_id="10" stage="1" lat="1">
<core>AddSub</core>
<MemPortIdVec></MemPortIdVec>
<condition id="-1">
<or_exp><and_exp></and_exp></or_exp>
</condition>

<Node id="68" bw="8" op_0_bw="8" op_1_bw="8">
<![CDATA[
._crit_edge1.i:2  %loop_53 = add i8 %loop_0_i, 1

]]></Node>
<StgValue><ssdm name="loop_53"/></StgValue>
</operation>

<operation id="77" st_id="10" stage="1" lat="1">
<core>NULL</core>
<MemPortIdVec></MemPortIdVec>
<condition id="-1">
<or_exp><and_exp></and_exp></or_exp>
</condition>

<Node id="69" bw="32" op_0_bw="32" op_1_bw="64" op_2_bw="64" op_3_bw="64">
<![CDATA[
._crit_edge1.i:3  %empty = call i32 (...)* @_ssdm_op_SpecLoopTripCount(i64 168, i64 168, i64 168)

]]></Node>
<StgValue><ssdm name="empty"/></StgValue>
</operation>

<operation id="78" st_id="10" stage="1" lat="1">
<core>NULL</core>
<MemPortIdVec></MemPortIdVec>
<condition id="-1">
<or_exp><and_exp></and_exp></or_exp>
</condition>

<Node id="70" bw="0" op_0_bw="1" op_1_bw="0" op_2_bw="0">
<![CDATA[
._crit_edge1.i:4  br i1 %icmp_ln393_1, label %KeccakP1600_ExtractBytes.exit, label %7

]]></Node>
<StgValue><ssdm name="br_ln393"/></StgValue>
</operation>

<operation id="79" st_id="10" stage="1" lat="1">
<core>NULL</core>
<MemPortIdVec></MemPortIdVec>
<condition id="-1">
<or_exp><and_exp><literal name="icmp_ln393_1" val="0"/>
</and_exp></or_exp>
</condition>

<Node id="72" bw="64" op_0_bw="8">
<![CDATA[
:0  %zext_ln394_1 = zext i8 %loop_0_i to i64

]]></Node>
<StgValue><ssdm name="zext_ln394_1"/></StgValue>
</operation>

<operation id="80" st_id="10" stage="1" lat="1">
<core>NULL</core>
<MemPortIdVec></MemPortIdVec>
<condition id="-1">
<or_exp><and_exp><literal name="icmp_ln393_1" val="0"/>
</and_exp></or_exp>
</condition>

<Node id="73" bw="9" op_0_bw="8">
<![CDATA[
:1  %zext_ln394_15 = zext i8 %loop_0_i to i9

]]></Node>
<StgValue><ssdm name="zext_ln394_15"/></StgValue>
</operation>

<operation id="81" st_id="10" stage="1" lat="1">
<core>NULL</core>
<MemPortIdVec></MemPortIdVec>
<condition id="-1">
<or_exp><and_exp><literal name="icmp_ln393_1" val="0"/>
</and_exp></or_exp>
</condition>

<Node id="74" bw="8" op_0_bw="8" op_1_bw="64" op_2_bw="64">
<![CDATA[
:2  %instance_state_addr_3 = getelementptr [200 x i8]* %instance_state, i64 0, i64 %zext_ln394_1

]]></Node>
<StgValue><ssdm name="instance_state_addr_3"/></StgValue>
</operation>

<operation id="82" st_id="10" stage="2" lat="2">
<core>RAM</core>
<MemPortIdVec>0 </MemPortIdVec>
<condition id="-1">
<or_exp><and_exp><literal name="icmp_ln393_1" val="0"/>
</and_exp></or_exp>
</condition>

<Node id="75" bw="8" op_0_bw="8">
<![CDATA[
:3  %instance_state_load_3 = load i8* %instance_state_addr_3, align 1

]]></Node>
<StgValue><ssdm name="instance_state_load_3"/></StgValue>
</operation>

<operation id="83" st_id="10" stage="1" lat="1">
<core>NULL</core>
<MemPortIdVec></MemPortIdVec>
<condition id="-1">
<or_exp><and_exp><literal name="icmp_ln393_1" val="0"/>
</and_exp></or_exp>
</condition>

<Node id="76" bw="9" op_0_bw="64">
<![CDATA[
:4  %trunc_ln304 = trunc i64 %curData_1_rec to i9

]]></Node>
<StgValue><ssdm name="trunc_ln304"/></StgValue>
</operation>

<operation id="84" st_id="10" stage="1" lat="1">
<core>TAddSub</core>
<MemPortIdVec></MemPortIdVec>
<condition id="-1">
<or_exp><and_exp><literal name="icmp_ln393_1" val="0"/>
</and_exp></or_exp>
</condition>

<Node id="77" bw="9" op_0_bw="9" op_1_bw="9">
<![CDATA[
:5  %add_ln394_3 = add i9 %zext_ln394_15, %trunc_ln304

]]></Node>
<StgValue><ssdm name="add_ln394_3"/></StgValue>
</operation>

<operation id="85" st_id="10" stage="1" lat="1">
<core>NULL</core>
<MemPortIdVec></MemPortIdVec>
<condition id="-1">
<or_exp><and_exp><literal name="icmp_ln393_1" val="0"/>
</and_exp></or_exp>
</condition>

<Node id="78" bw="9" op_0_bw="64">
<![CDATA[
:6  %trunc_ln302_4 = trunc i64 %curData_0_idx to i9

]]></Node>
<StgValue><ssdm name="trunc_ln302_4"/></StgValue>
</operation>

<operation id="86" st_id="10" stage="1" lat="1">
<core>TAddSub</core>
<MemPortIdVec></MemPortIdVec>
<condition id="-1">
<or_exp><and_exp><literal name="icmp_ln393_1" val="0"/>
</and_exp></or_exp>
</condition>

<Node id="79" bw="9" op_0_bw="9" op_1_bw="9">
<![CDATA[
:7  %add_ln394_2 = add i9 %trunc_ln302_4, %add_ln394_3

]]></Node>
<StgValue><ssdm name="add_ln394_2"/></StgValue>
</operation>

<operation id="87" st_id="10" stage="1" lat="1">
<core>NULL</core>
<MemPortIdVec></MemPortIdVec>
<condition id="-1">
<or_exp><and_exp><literal name="icmp_ln393_1" val="0"/>
</and_exp></or_exp>
</condition>

<Node id="80" bw="10" op_0_bw="9">
<![CDATA[
:8  %zext_ln394_16 = zext i9 %add_ln394_2 to i10

]]></Node>
<StgValue><ssdm name="zext_ln394_16"/></StgValue>
</operation>

<operation id="88" st_id="10" stage="1" lat="1">
<core>AddSub</core>
<MemPortIdVec></MemPortIdVec>
<condition id="-1">
<or_exp><and_exp><literal name="icmp_ln393_1" val="0"/>
</and_exp></or_exp>
</condition>

<Node id="81" bw="10" op_0_bw="10" op_1_bw="10">
<![CDATA[
:9  %add_ln394_11 = add i10 %select_ln394, %zext_ln394_16

]]></Node>
<StgValue><ssdm name="add_ln394_11"/></StgValue>
</operation>

<operation id="89" st_id="10" stage="1" lat="1">
<core>AddSub</core>
<MemPortIdVec></MemPortIdVec>
<condition id="-1">
<or_exp><and_exp><literal name="icmp_ln393_1" val="1"/>
</and_exp></or_exp>
</condition>

<Node id="87" bw="64" op_0_bw="64" op_1_bw="64">
<![CDATA[
KeccakP1600_ExtractBytes.exit:0  %add_ln310 = add i64 %curData_1_rec, 168

]]></Node>
<StgValue><ssdm name="add_ln310"/></StgValue>
</operation>

<operation id="90" st_id="10" stage="1" lat="1">
<core>AddSub</core>
<MemPortIdVec></MemPortIdVec>
<condition id="-1">
<or_exp><and_exp><literal name="icmp_ln393_1" val="1"/>
</and_exp></or_exp>
</condition>

<Node id="88" bw="64" op_0_bw="64" op_1_bw="64">
<![CDATA[
KeccakP1600_ExtractBytes.exit:1  %j_18 = add i64 %j_0, -168

]]></Node>
<StgValue><ssdm name="j_18"/></StgValue>
</operation>

<operation id="91" st_id="10" stage="1" lat="1">
<core>NULL</core>
<MemPortIdVec></MemPortIdVec>
<condition id="-1">
<or_exp><and_exp><literal name="icmp_ln393_1" val="1"/>
</and_exp></or_exp>
</condition>

<Node id="89" bw="0" op_0_bw="0">
<![CDATA[
KeccakP1600_ExtractBytes.exit:2  br label %5

]]></Node>
<StgValue><ssdm name="br_ln304"/></StgValue>
</operation>
</state>

<state id="11" st_id="11">

<operation id="92" st_id="11" stage="1" lat="2">
<core>RAM</core>
<MemPortIdVec>0 </MemPortIdVec>
<condition id="-1">
<or_exp><and_exp></and_exp></or_exp>
</condition>

<Node id="75" bw="8" op_0_bw="8">
<![CDATA[
:3  %instance_state_load_3 = load i8* %instance_state_addr_3, align 1

]]></Node>
<StgValue><ssdm name="instance_state_load_3"/></StgValue>
</operation>

<operation id="93" st_id="11" stage="1" lat="1">
<core>NULL</core>
<MemPortIdVec></MemPortIdVec>
<condition id="-1">
<or_exp><and_exp></and_exp></or_exp>
</condition>

<Node id="82" bw="64" op_0_bw="10">
<![CDATA[
:10  %sext_ln394_1 = sext i10 %add_ln394_11 to i64

]]></Node>
<StgValue><ssdm name="sext_ln394_1"/></StgValue>
</operation>

<operation id="94" st_id="11" stage="1" lat="1">
<core>NULL</core>
<MemPortIdVec></MemPortIdVec>
<condition id="-1">
<or_exp><and_exp></and_exp></or_exp>
</condition>

<Node id="83" bw="9" op_0_bw="8" op_1_bw="64" op_2_bw="64">
<![CDATA[
:11  %data_0_addr_1 = getelementptr [498 x i8]* %data_0, i64 0, i64 %sext_ln394_1

]]></Node>
<StgValue><ssdm name="data_0_addr_1"/></StgValue>
</operation>

<operation id="95" st_id="11" stage="1" lat="1">
<core>RAM</core>
<MemPortIdVec>0 </MemPortIdVec>
<condition id="-1">
<or_exp><and_exp></and_exp></or_exp>
</condition>

<Node id="84" bw="0" op_0_bw="8" op_1_bw="9">
<![CDATA[
:12  store i8 %instance_state_load_3, i8* %data_0_addr_1, align 1

]]></Node>
<StgValue><ssdm name="store_ln394"/></StgValue>
</operation>

<operation id="96" st_id="11" stage="1" lat="1">
<core>NULL</core>
<MemPortIdVec></MemPortIdVec>
<condition id="-1">
<or_exp><and_exp></and_exp></or_exp>
</condition>

<Node id="85" bw="0" op_0_bw="0">
<![CDATA[
:13  br label %._crit_edge1.i

]]></Node>
<StgValue><ssdm name="br_ln393"/></StgValue>
</operation>
</state>

<state id="12" st_id="12">

<operation id="97" st_id="12" stage="1" lat="2">
<core></core>
<MemPortIdVec></MemPortIdVec>
<condition id="-1">
<or_exp><and_exp><literal name="icmp_ln303" val="1"/>
</and_exp></or_exp>
</condition>

<Node id="97" bw="0" op_0_bw="0" op_1_bw="8" op_2_bw="6" op_3_bw="64" op_4_bw="0">
<![CDATA[
._crit_edge1:0  call fastcc void @KeccakP1600_Permute_([200 x i8]* %instance_state)

]]></Node>
<StgValue><ssdm name="call_ln317"/></StgValue>
</operation>

<operation id="98" st_id="12" stage="1" lat="1">
<core>NULL</core>
<MemPortIdVec></MemPortIdVec>
<condition id="-1">
<or_exp><and_exp><literal name="icmp_ln303" val="1"/>
</and_exp></or_exp>
</condition>

<Node id="98" bw="0" op_0_bw="0">
<![CDATA[
._crit_edge1:1  br label %._crit_edge3.critedge

]]></Node>
<StgValue><ssdm name="br_ln319"/></StgValue>
</operation>

<operation id="99" st_id="12" stage="1" lat="1">
<core>NULL</core>
<MemPortIdVec></MemPortIdVec>
<condition id="-1">
<or_exp><and_exp></and_exp></or_exp>
</condition>

<Node id="101" bw="32" op_0_bw="34">
<![CDATA[
._crit_edge3.critedge:1  %trunc_ln320 = trunc i34 %i_36_load to i32

]]></Node>
<StgValue><ssdm name="trunc_ln320"/></StgValue>
</operation>

<operation id="100" st_id="12" stage="1" lat="1">
<core>AddSub</core>
<MemPortIdVec></MemPortIdVec>
<condition id="-1">
<or_exp><and_exp></and_exp></or_exp>
</condition>

<Node id="102" bw="32" op_0_bw="32" op_1_bw="32">
<![CDATA[
._crit_edge3.critedge:2  %partialBlock = sub i32 %zext_ln320, %trunc_ln320

]]></Node>
<StgValue><ssdm name="partialBlock"/></StgValue>
</operation>
</state>

<state id="13" st_id="13">

<operation id="101" st_id="13" stage="1" lat="1">
<core>NULL</core>
<MemPortIdVec></MemPortIdVec>
<condition id="-1">
<or_exp><and_exp></and_exp></or_exp>
</condition>

<Node id="100" bw="32" op_0_bw="32" op_1_bw="0" op_2_bw="32" op_3_bw="0">
<![CDATA[
._crit_edge3.critedge:0  %offset_assign_1 = phi i32 [ 0, %._crit_edge1 ], [ %instance_byteIOIndex_1, %2 ]

]]></Node>
<StgValue><ssdm name="offset_assign_1"/></StgValue>
</operation>

<operation id="102" st_id="13" stage="1" lat="1">
<core>AddSub</core>
<MemPortIdVec></MemPortIdVec>
<condition id="-1">
<or_exp><and_exp></and_exp></or_exp>
</condition>

<Node id="103" bw="32" op_0_bw="32" op_1_bw="32">
<![CDATA[
._crit_edge3.critedge:3  %add_ln321 = add i32 %offset_assign_1, %partialBlock

]]></Node>
<StgValue><ssdm name="add_ln321"/></StgValue>
</operation>

<operation id="103" st_id="13" stage="1" lat="1">
<core>Cmp</core>
<MemPortIdVec></MemPortIdVec>
<condition id="-1">
<or_exp><and_exp></and_exp></or_exp>
</condition>

<Node id="104" bw="1" op_0_bw="32" op_1_bw="32">
<![CDATA[
._crit_edge3.critedge:4  %icmp_ln321 = icmp ugt i32 %add_ln321, 168

]]></Node>
<StgValue><ssdm name="icmp_ln321"/></StgValue>
</operation>

<operation id="104" st_id="13" stage="1" lat="1">
<core>AddSub</core>
<MemPortIdVec></MemPortIdVec>
<condition id="-1">
<or_exp><and_exp></and_exp></or_exp>
</condition>

<Node id="105" bw="32" op_0_bw="32" op_1_bw="32">
<![CDATA[
._crit_edge3.critedge:5  %partialBlock_17 = sub i32 168, %offset_assign_1

]]></Node>
<StgValue><ssdm name="partialBlock_17"/></StgValue>
</operation>

<operation id="105" st_id="13" stage="1" lat="1">
<core>Sel</core>
<MemPortIdVec></MemPortIdVec>
<condition id="-1">
<or_exp><and_exp></and_exp></or_exp>
</condition>

<Node id="106" bw="32" op_0_bw="1" op_1_bw="32" op_2_bw="32">
<![CDATA[
._crit_edge3.critedge:6  %partialBlock_18 = select i1 %icmp_ln321, i32 %partialBlock_17, i32 %partialBlock

]]></Node>
<StgValue><ssdm name="partialBlock_18"/></StgValue>
</operation>

<operation id="106" st_id="13" stage="1" lat="1">
<core>NULL</core>
<MemPortIdVec></MemPortIdVec>
<condition id="-1">
<or_exp><and_exp></and_exp></or_exp>
</condition>

<Node id="107" bw="64" op_0_bw="32">
<![CDATA[
._crit_edge3.critedge:7  %zext_ln323 = zext i32 %partialBlock_18 to i64

]]></Node>
<StgValue><ssdm name="zext_ln323"/></StgValue>
</operation>

<operation id="107" st_id="13" stage="1" lat="1">
<core>NULL</core>
<MemPortIdVec></MemPortIdVec>
<condition id="-1">
<or_exp><and_exp></and_exp></or_exp>
</condition>

<Node id="108" bw="34" op_0_bw="32">
<![CDATA[
._crit_edge3.critedge:8  %zext_ln323_4 = zext i32 %partialBlock_18 to i34

]]></Node>
<StgValue><ssdm name="zext_ln323_4"/></StgValue>
</operation>

<operation id="108" st_id="13" stage="1" lat="1">
<core>AddSub</core>
<MemPortIdVec></MemPortIdVec>
<condition id="-1">
<or_exp><and_exp></and_exp></or_exp>
</condition>

<Node id="109" bw="34" op_0_bw="34" op_1_bw="34">
<![CDATA[
._crit_edge3.critedge:9  %i = add i34 %i_36_load, %zext_ln323_4

]]></Node>
<StgValue><ssdm name="i"/></StgValue>
</operation>

<operation id="109" st_id="13" stage="1" lat="1">
<core>NULL</core>
<MemPortIdVec></MemPortIdVec>
<condition id="-1">
<or_exp><and_exp></and_exp></or_exp>
</condition>

<Node id="110" bw="0" op_0_bw="0">
<![CDATA[
._crit_edge3.critedge:10  br label %._crit_edge1.i3

]]></Node>
<StgValue><ssdm name="br_ln390"/></StgValue>
</operation>
</state>

<state id="14" st_id="14">

<operation id="110" st_id="14" stage="1" lat="1">
<core>NULL</core>
<MemPortIdVec></MemPortIdVec>
<condition id="-1">
<or_exp><and_exp></and_exp></or_exp>
</condition>

<Node id="112" bw="32" op_0_bw="32" op_1_bw="0" op_2_bw="32" op_3_bw="0">
<![CDATA[
._crit_edge1.i3:0  %loop_0_i1 = phi i32 [ %loop, %9 ], [ 0, %._crit_edge3.critedge ]

]]></Node>
<StgValue><ssdm name="loop_0_i1"/></StgValue>
</operation>

<operation id="111" st_id="14" stage="1" lat="1">
<core>Cmp</core>
<MemPortIdVec></MemPortIdVec>
<condition id="-1">
<or_exp><and_exp></and_exp></or_exp>
</condition>

<Node id="113" bw="1" op_0_bw="32" op_1_bw="32">
<![CDATA[
._crit_edge1.i3:1  %icmp_ln393 = icmp eq i32 %loop_0_i1, %partialBlock_18

]]></Node>
<StgValue><ssdm name="icmp_ln393"/></StgValue>
</operation>

<operation id="112" st_id="14" stage="1" lat="1">
<core>AddSub</core>
<MemPortIdVec></MemPortIdVec>
<condition id="-1">
<or_exp><and_exp></and_exp></or_exp>
</condition>

<Node id="114" bw="32" op_0_bw="32" op_1_bw="32">
<![CDATA[
._crit_edge1.i3:2  %loop = add nsw i32 %loop_0_i1, 1

]]></Node>
<StgValue><ssdm name="loop"/></StgValue>
</operation>

<operation id="113" st_id="14" stage="1" lat="1">
<core>NULL</core>
<MemPortIdVec></MemPortIdVec>
<condition id="-1">
<or_exp><and_exp></and_exp></or_exp>
</condition>

<Node id="115" bw="0" op_0_bw="1" op_1_bw="0" op_2_bw="0">
<![CDATA[
._crit_edge1.i3:3  br i1 %icmp_ln393, label %KeccakP1600_ExtractBytes.exit11, label %9

]]></Node>
<StgValue><ssdm name="br_ln393"/></StgValue>
</operation>

<operation id="114" st_id="14" stage="1" lat="1">
<core>AddSub</core>
<MemPortIdVec></MemPortIdVec>
<condition id="-1">
<or_exp><and_exp><literal name="icmp_ln393" val="0"/>
</and_exp></or_exp>
</condition>

<Node id="117" bw="32" op_0_bw="32" op_1_bw="32">
<![CDATA[
:0  %add_ln394 = add i32 %offset_assign_1, %loop_0_i1

]]></Node>
<StgValue><ssdm name="add_ln394"/></StgValue>
</operation>

<operation id="115" st_id="14" stage="1" lat="1">
<core>NULL</core>
<MemPortIdVec></MemPortIdVec>
<condition id="-1">
<or_exp><and_exp><literal name="icmp_ln393" val="0"/>
</and_exp></or_exp>
</condition>

<Node id="118" bw="64" op_0_bw="32">
<![CDATA[
:1  %zext_ln394 = zext i32 %add_ln394 to i64

]]></Node>
<StgValue><ssdm name="zext_ln394"/></StgValue>
</operation>

<operation id="116" st_id="14" stage="1" lat="1">
<core>NULL</core>
<MemPortIdVec></MemPortIdVec>
<condition id="-1">
<or_exp><and_exp><literal name="icmp_ln393" val="0"/>
</and_exp></or_exp>
</condition>

<Node id="119" bw="8" op_0_bw="8" op_1_bw="64" op_2_bw="64">
<![CDATA[
:2  %instance_state_addr_2 = getelementptr [200 x i8]* %instance_state, i64 0, i64 %zext_ln394

]]></Node>
<StgValue><ssdm name="instance_state_addr_2"/></StgValue>
</operation>

<operation id="117" st_id="14" stage="2" lat="2">
<core>RAM</core>
<MemPortIdVec>0 </MemPortIdVec>
<condition id="-1">
<or_exp><and_exp><literal name="icmp_ln393" val="0"/>
</and_exp></or_exp>
</condition>

<Node id="120" bw="8" op_0_bw="8">
<![CDATA[
:3  %instance_state_load_2 = load i8* %instance_state_addr_2, align 1

]]></Node>
<StgValue><ssdm name="instance_state_load_2"/></StgValue>
</operation>

<operation id="118" st_id="14" stage="1" lat="1">
<core>NULL</core>
<MemPortIdVec></MemPortIdVec>
<condition id="-1">
<or_exp><and_exp><literal name="icmp_ln393" val="0"/>
</and_exp></or_exp>
</condition>

<Node id="121" bw="9" op_0_bw="32">
<![CDATA[
:4  %trunc_ln394 = trunc i32 %loop_0_i1 to i9

]]></Node>
<StgValue><ssdm name="trunc_ln394"/></StgValue>
</operation>

<operation id="119" st_id="14" stage="1" lat="1">
<core>NULL</core>
<MemPortIdVec></MemPortIdVec>
<condition id="-1">
<or_exp><and_exp><literal name="icmp_ln393" val="0"/>
</and_exp></or_exp>
</condition>

<Node id="122" bw="9" op_0_bw="64">
<![CDATA[
:5  %trunc_ln302 = trunc i64 %curData_0_idx to i9

]]></Node>
<StgValue><ssdm name="trunc_ln302"/></StgValue>
</operation>

<operation id="120" st_id="14" stage="1" lat="1">
<core>AddSub</core>
<MemPortIdVec></MemPortIdVec>
<condition id="-1">
<or_exp><and_exp><literal name="icmp_ln393" val="0"/>
</and_exp></or_exp>
</condition>

<Node id="123" bw="9" op_0_bw="9" op_1_bw="9">
<![CDATA[
:6  %add_ln394_1 = add i9 %trunc_ln394, %trunc_ln302

]]></Node>
<StgValue><ssdm name="add_ln394_1"/></StgValue>
</operation>

<operation id="121" st_id="14" stage="1" lat="1">
<core>NULL</core>
<MemPortIdVec></MemPortIdVec>
<condition id="-1">
<or_exp><and_exp><literal name="icmp_ln393" val="0"/>
</and_exp></or_exp>
</condition>

<Node id="124" bw="10" op_0_bw="9">
<![CDATA[
:7  %zext_ln394_14 = zext i9 %add_ln394_1 to i10

]]></Node>
<StgValue><ssdm name="zext_ln394_14"/></StgValue>
</operation>

<operation id="122" st_id="14" stage="1" lat="1">
<core>AddSub</core>
<MemPortIdVec></MemPortIdVec>
<condition id="-1">
<or_exp><and_exp><literal name="icmp_ln393" val="0"/>
</and_exp></or_exp>
</condition>

<Node id="125" bw="10" op_0_bw="10" op_1_bw="10">
<![CDATA[
:8  %add_ln394_10 = add i10 %select_ln394, %zext_ln394_14

]]></Node>
<StgValue><ssdm name="add_ln394_10"/></StgValue>
</operation>

<operation id="123" st_id="14" stage="1" lat="1">
<core>AddSub</core>
<MemPortIdVec></MemPortIdVec>
<condition id="-1">
<or_exp><and_exp><literal name="icmp_ln393" val="1"/>
</and_exp></or_exp>
</condition>

<Node id="131" bw="32" op_0_bw="32" op_1_bw="32">
<![CDATA[
KeccakP1600_ExtractBytes.exit11:0  %add_ln330 = add i32 %offset_assign_1, %partialBlock_18

]]></Node>
<StgValue><ssdm name="add_ln330"/></StgValue>
</operation>

<operation id="124" st_id="14" stage="1" lat="1">
<core>NULL</core>
<MemPortIdVec></MemPortIdVec>
<condition id="-1">
<or_exp><and_exp><literal name="icmp_ln393" val="1"/>
</and_exp></or_exp>
</condition>

<Node id="132" bw="0" op_0_bw="34" op_1_bw="34" op_2_bw="0" op_3_bw="34">
<![CDATA[
KeccakP1600_ExtractBytes.exit11:1  store i34 %i, i34* %i_36

]]></Node>
<StgValue><ssdm name="store_ln323"/></StgValue>
</operation>

<operation id="125" st_id="14" stage="1" lat="1">
<core>NULL</core>
<MemPortIdVec></MemPortIdVec>
<condition id="-1">
<or_exp><and_exp><literal name="icmp_ln393" val="1"/>
</and_exp></or_exp>
</condition>

<Node id="133" bw="0" op_0_bw="0">
<![CDATA[
KeccakP1600_ExtractBytes.exit11:2  br label %.backedge.backedge

]]></Node>
<StgValue><ssdm name="br_ln0"/></StgValue>
</operation>
</state>

<state id="15" st_id="15">

<operation id="126" st_id="15" stage="1" lat="2">
<core>RAM</core>
<MemPortIdVec>0 </MemPortIdVec>
<condition id="-1">
<or_exp><and_exp></and_exp></or_exp>
</condition>

<Node id="120" bw="8" op_0_bw="8">
<![CDATA[
:3  %instance_state_load_2 = load i8* %instance_state_addr_2, align 1

]]></Node>
<StgValue><ssdm name="instance_state_load_2"/></StgValue>
</operation>

<operation id="127" st_id="15" stage="1" lat="1">
<core>NULL</core>
<MemPortIdVec></MemPortIdVec>
<condition id="-1">
<or_exp><and_exp></and_exp></or_exp>
</condition>

<Node id="126" bw="64" op_0_bw="10">
<![CDATA[
:9  %sext_ln394 = sext i10 %add_ln394_10 to i64

]]></Node>
<StgValue><ssdm name="sext_ln394"/></StgValue>
</operation>

<operation id="128" st_id="15" stage="1" lat="1">
<core>NULL</core>
<MemPortIdVec></MemPortIdVec>
<condition id="-1">
<or_exp><and_exp></and_exp></or_exp>
</condition>

<Node id="127" bw="9" op_0_bw="8" op_1_bw="64" op_2_bw="64">
<![CDATA[
:10  %data_0_addr = getelementptr [498 x i8]* %data_0, i64 0, i64 %sext_ln394

]]></Node>
<StgValue><ssdm name="data_0_addr"/></StgValue>
</operation>

<operation id="129" st_id="15" stage="1" lat="1">
<core>RAM</core>
<MemPortIdVec>0 </MemPortIdVec>
<condition id="-1">
<or_exp><and_exp></and_exp></or_exp>
</condition>

<Node id="128" bw="0" op_0_bw="8" op_1_bw="9">
<![CDATA[
:11  store i8 %instance_state_load_2, i8* %data_0_addr, align 1

]]></Node>
<StgValue><ssdm name="store_ln394"/></StgValue>
</operation>

<operation id="130" st_id="15" stage="1" lat="1">
<core>NULL</core>
<MemPortIdVec></MemPortIdVec>
<condition id="-1">
<or_exp><and_exp></and_exp></or_exp>
</condition>

<Node id="129" bw="0" op_0_bw="0">
<![CDATA[
:12  br label %._crit_edge1.i3

]]></Node>
<StgValue><ssdm name="br_ln393"/></StgValue>
</operation>
</state>

<state id="16" st_id="16">

<operation id="131" st_id="16" stage="1" lat="1">
<core>NULL</core>
<MemPortIdVec></MemPortIdVec>
<condition id="-1">
<or_exp><and_exp></and_exp></or_exp>
</condition>

<Node id="135" bw="32" op_0_bw="32" op_1_bw="0" op_2_bw="32" op_3_bw="0">
<![CDATA[
.backedge.backedge:0  %instance_byteIOIndex_3 = phi i32 [ %add_ln330, %KeccakP1600_ExtractBytes.exit11 ], [ 168, %8 ]

]]></Node>
<StgValue><ssdm name="instance_byteIOIndex_3"/></StgValue>
</operation>

<operation id="132" st_id="16" stage="1" lat="1">
<core>NULL</core>
<MemPortIdVec></MemPortIdVec>
<condition id="-1">
<or_exp><and_exp></and_exp></or_exp>
</condition>

<Node id="136" bw="64" op_0_bw="64" op_1_bw="0" op_2_bw="64" op_3_bw="0">
<![CDATA[
.backedge.backedge:1  %curData_1_rec_pn = phi i64 [ %zext_ln323, %KeccakP1600_ExtractBytes.exit11 ], [ %curData_1_rec, %8 ]

]]></Node>
<StgValue><ssdm name="curData_1_rec_pn"/></StgValue>
</operation>

<operation id="133" st_id="16" stage="1" lat="1">
<core>AddSub</core>
<MemPortIdVec></MemPortIdVec>
<condition id="-1">
<or_exp><and_exp></and_exp></or_exp>
</condition>

<Node id="137" bw="64" op_0_bw="64" op_1_bw="64">
<![CDATA[
.backedge.backedge:2  %add_ln329 = add i64 %curData_1_rec_pn, %curData_0_idx

]]></Node>
<StgValue><ssdm name="add_ln329"/></StgValue>
</operation>

<operation id="134" st_id="16" stage="1" lat="1">
<core>NULL</core>
<MemPortIdVec></MemPortIdVec>
<condition id="-1">
<or_exp><and_exp></and_exp></or_exp>
</condition>

<Node id="138" bw="0" op_0_bw="0">
<![CDATA[
.backedge.backedge:3  br label %.backedge

]]></Node>
<StgValue><ssdm name="br_ln0"/></StgValue>
</operation>
</state>
</state_list>


<ports>
<port id="163" name="instance_state" dir="2" iftype="1">
<core>RAM</core><StgValue><ssdm name="instance_state"/><MemPortTyVec>2 3 </MemPortTyVec>
</StgValue>
</port>
<port id="164" name="instance_byteIOIndex_read" dir="0" iftype="0">
<core>NULL</core><StgValue><ssdm name="instance_byteIOIndex_read"/></StgValue>
</port>
<port id="165" name="instance_squeezing_read" dir="0" iftype="0">
<core>NULL</core><StgValue><ssdm name="instance_squeezing_read"/></StgValue>
</port>
<port id="166" name="data_0" dir="1" iftype="1">
<core>RAM</core><StgValue><ssdm name="data_0"/><MemPortTyVec>0 3 </MemPortTyVec>
</StgValue>
</port>
<port id="167" name="data_offset1" dir="0" iftype="0">
<core>NULL</core><StgValue><ssdm name="data_offset1"/></StgValue>
</port>
<port id="168" name="dataByteLen" dir="0" iftype="0">
<core>NULL</core><StgValue><ssdm name="dataByteLen"/></StgValue>
</port>
<port id="169" name="KeccakRhoOffsets" dir="0" iftype="1">
<core>ROM_nP</core><StgValue><ssdm name="KeccakRhoOffsets"/><MemPortTyVec>1 </MemPortTyVec>
</StgValue>
</port>
<port id="170" name="KeccakRoundConstants" dir="0" iftype="1">
<core>ROM_nP</core><StgValue><ssdm name="KeccakRoundConstants"/><MemPortTyVec>1 </MemPortTyVec>
</StgValue>
</port>
</ports>


<dataflows>
<dataflow id="172" from="_ssdm_op_Read.ap_auto.i8" to="dataByteLen_read" fromId="171" toId="17">
</dataflow>
<dataflow id="173" from="dataByteLen" to="dataByteLen_read" fromId="168" toId="17">
</dataflow>
<dataflow id="175" from="_ssdm_op_Read.ap_auto.i1" to="data_offset1_read" fromId="174" toId="18">
</dataflow>
<dataflow id="176" from="data_offset1" to="data_offset1_read" fromId="167" toId="18">
</dataflow>
<dataflow id="178" from="_ssdm_op_Read.ap_auto.i32" to="instance_squeezing_r" fromId="177" toId="19">
</dataflow>
<dataflow id="179" from="instance_squeezing_read" to="instance_squeezing_r" fromId="165" toId="19">
</dataflow>
<dataflow id="180" from="_ssdm_op_Read.ap_auto.i32" to="instance_byteIOIndex_68" fromId="177" toId="20">
</dataflow>
<dataflow id="181" from="instance_byteIOIndex_read" to="instance_byteIOIndex_68" fromId="164" toId="20">
</dataflow>
<dataflow id="182" from="dataByteLen_read" to="dataByteLen_cast" fromId="17" toId="21">
</dataflow>
<dataflow id="183" from="dataByteLen_cast" to="zext_ln394_13" fromId="21" toId="22">
</dataflow>
<dataflow id="184" from="data_offset1_read" to="select_ln394" fromId="18" toId="23">
</dataflow>
<dataflow id="186" from="StgValue_185" to="select_ln394" fromId="185" toId="23">
</dataflow>
<dataflow id="188" from="StgValue_187" to="select_ln394" fromId="187" toId="23">
</dataflow>
<dataflow id="189" from="instance_squeezing_r" to="icmp_ln297" fromId="19" toId="24">
</dataflow>
<dataflow id="191" from="StgValue_190" to="icmp_ln297" fromId="190" toId="24">
</dataflow>
<dataflow id="192" from="icmp_ln297" to="br_ln297" fromId="24" toId="25">
</dataflow>
<dataflow id="193" from="instance_byteIOIndex_68" to="zext_ln149" fromId="20" toId="26">
</dataflow>
<dataflow id="194" from="instance_state" to="instance_state_addr" fromId="163" toId="27">
</dataflow>
<dataflow id="196" from="StgValue_195" to="instance_state_addr" fromId="195" toId="27">
</dataflow>
<dataflow id="197" from="zext_ln149" to="instance_state_addr" fromId="26" toId="27">
</dataflow>
<dataflow id="198" from="instance_state_addr" to="instance_state_load" fromId="27" toId="28">
</dataflow>
<dataflow id="199" from="instance_state_addr" to="instance_state_load" fromId="27" toId="29">
</dataflow>
<dataflow id="200" from="instance_state_load" to="xor_ln149" fromId="29" toId="30">
</dataflow>
<dataflow id="202" from="StgValue_201" to="xor_ln149" fromId="201" toId="30">
</dataflow>
<dataflow id="203" from="xor_ln149" to="store_ln149" fromId="30" toId="31">
</dataflow>
<dataflow id="204" from="instance_state_addr" to="store_ln149" fromId="27" toId="31">
</dataflow>
<dataflow id="205" from="instance_state" to="instance_state_addr_1" fromId="163" toId="32">
</dataflow>
<dataflow id="206" from="StgValue_195" to="instance_state_addr_1" fromId="195" toId="32">
</dataflow>
<dataflow id="208" from="StgValue_207" to="instance_state_addr_1" fromId="207" toId="32">
</dataflow>
<dataflow id="209" from="instance_state_addr_1" to="instance_state_load_1" fromId="32" toId="33">
</dataflow>
<dataflow id="210" from="instance_state_addr_1" to="instance_state_load_1" fromId="32" toId="34">
</dataflow>
<dataflow id="211" from="instance_state_load_1" to="xor_ln149_1" fromId="34" toId="35">
</dataflow>
<dataflow id="213" from="StgValue_212" to="xor_ln149_1" fromId="212" toId="35">
</dataflow>
<dataflow id="214" from="xor_ln149_1" to="store_ln149" fromId="35" toId="36">
</dataflow>
<dataflow id="215" from="instance_state_addr_1" to="store_ln149" fromId="32" toId="36">
</dataflow>
<dataflow id="217" from="KeccakP1600_Permute_" to="call_ln279" fromId="216" toId="37">
</dataflow>
<dataflow id="218" from="instance_state" to="call_ln279" fromId="163" toId="37">
</dataflow>
<dataflow id="219" from="KeccakRhoOffsets" to="call_ln279" fromId="169" toId="37">
</dataflow>
<dataflow id="220" from="KeccakRoundConstants" to="call_ln279" fromId="170" toId="37">
</dataflow>
<dataflow id="221" from="KeccakP1600_Permute_" to="call_ln279" fromId="216" toId="38">
</dataflow>
<dataflow id="222" from="instance_state" to="call_ln279" fromId="163" toId="38">
</dataflow>
<dataflow id="223" from="KeccakRhoOffsets" to="call_ln279" fromId="169" toId="38">
</dataflow>
<dataflow id="224" from="KeccakRoundConstants" to="call_ln279" fromId="170" toId="38">
</dataflow>
<dataflow id="225" from="StgValue_190" to="instance_byteIOIndex" fromId="190" toId="40">
<condition id="-1">
<or_exp><and_exp><literal name="icmp_ln297" val="1"/>
</and_exp></or_exp>
</condition>
</dataflow>
<dataflow id="226" from="br_ln298" to="instance_byteIOIndex" fromId="39" toId="40">
</dataflow>
<dataflow id="227" from="instance_byteIOIndex_68" to="instance_byteIOIndex" fromId="20" toId="40">
<condition id="-1">
<or_exp><and_exp><literal name="icmp_ln297" val="0"/>
</and_exp></or_exp>
</condition>
</dataflow>
<dataflow id="228" from="br_ln297" to="instance_byteIOIndex" fromId="25" toId="40">
</dataflow>
<dataflow id="230" from="StgValue_229" to="i_36" fromId="229" toId="41">
</dataflow>
<dataflow id="231" from="dataByteLen_cast" to="zext_ln303" fromId="21" toId="42">
</dataflow>
<dataflow id="232" from="dataByteLen_cast" to="zext_ln320" fromId="21" toId="43">
</dataflow>
<dataflow id="234" from="StgValue_233" to="store_ln302" fromId="233" toId="44">
</dataflow>
<dataflow id="235" from="i_36" to="store_ln302" fromId="41" toId="44">
</dataflow>
<dataflow id="236" from="instance_byteIOIndex" to="instance_byteIOIndex_1" fromId="40" toId="46">
<condition id="-1">
<or_exp><and_exp></and_exp></or_exp>
</condition>
</dataflow>
<dataflow id="237" from="br_ln302" to="instance_byteIOIndex_1" fromId="45" toId="46">
</dataflow>
<dataflow id="238" from="instance_byteIOIndex_3" to="instance_byteIOIndex_1" fromId="131" toId="46">
<BackEdge/>
<condition id="-1">
<or_exp><and_exp></and_exp></or_exp>
</condition>
</dataflow>
<dataflow id="239" from="br_ln0" to="instance_byteIOIndex_1" fromId="134" toId="46">
<BackEdge/>
</dataflow>
<dataflow id="240" from="StgValue_195" to="curData_0_idx" fromId="195" toId="47">
<condition id="-1">
<or_exp><and_exp></and_exp></or_exp>
</condition>
</dataflow>
<dataflow id="241" from="br_ln302" to="curData_0_idx" fromId="45" toId="47">
</dataflow>
<dataflow id="242" from="add_ln329" to="curData_0_idx" fromId="133" toId="47">
<BackEdge/>
<condition id="-1">
<or_exp><and_exp></and_exp></or_exp>
</condition>
</dataflow>
<dataflow id="243" from="br_ln0" to="curData_0_idx" fromId="134" toId="47">
<BackEdge/>
</dataflow>
<dataflow id="244" from="i_36" to="i_36_load" fromId="41" toId="48">
</dataflow>
<dataflow id="245" from="i_36_load" to="icmp_ln302" fromId="48" toId="49">
</dataflow>
<dataflow id="246" from="zext_ln394_13" to="icmp_ln302" fromId="22" toId="49">
</dataflow>
<dataflow id="247" from="icmp_ln302" to="br_ln302" fromId="49" toId="50">
</dataflow>
<dataflow id="248" from="instance_byteIOIndex_1" to="icmp_ln303" fromId="46" toId="51">
</dataflow>
<dataflow id="250" from="StgValue_249" to="icmp_ln303" fromId="249" toId="51">
</dataflow>
<dataflow id="251" from="icmp_ln303" to="br_ln303" fromId="51" toId="52">
</dataflow>
<dataflow id="252" from="i_36_load" to="trunc_ln303" fromId="48" toId="53">
</dataflow>
<dataflow id="254" from="StgValue_253" to="add_ln303" fromId="253" toId="54">
</dataflow>
<dataflow id="255" from="trunc_ln303" to="add_ln303" fromId="53" toId="54">
</dataflow>
<dataflow id="256" from="add_ln303" to="icmp_ln303_1" fromId="54" toId="55">
</dataflow>
<dataflow id="257" from="zext_ln303" to="icmp_ln303_1" fromId="42" toId="55">
</dataflow>
<dataflow id="258" from="icmp_ln303_1" to="br_ln303" fromId="55" toId="56">
</dataflow>
<dataflow id="259" from="zext_ln394_13" to="j" fromId="22" toId="57">
</dataflow>
<dataflow id="260" from="i_36_load" to="j" fromId="48" toId="57">
</dataflow>
<dataflow id="261" from="j" to="sext_ln304" fromId="57" toId="58">
</dataflow>
<dataflow id="262" from="KeccakP1600_Permute_" to="call_ln317" fromId="216" toId="60">
</dataflow>
<dataflow id="263" from="instance_state" to="call_ln317" fromId="163" toId="60">
</dataflow>
<dataflow id="264" from="KeccakRhoOffsets" to="call_ln317" fromId="169" toId="60">
</dataflow>
<dataflow id="265" from="KeccakRoundConstants" to="call_ln317" fromId="170" toId="60">
</dataflow>
<dataflow id="266" from="sext_ln304" to="j_0" fromId="58" toId="62">
<condition id="-1">
<or_exp><and_exp><literal name="icmp_ln302" val="1"/>
<literal name="icmp_ln303" val="1"/>
<literal name="icmp_ln303_1" val="0"/>
</and_exp></or_exp>
</condition>
</dataflow>
<dataflow id="267" from="br_ln304" to="j_0" fromId="59" toId="62">
</dataflow>
<dataflow id="268" from="j_18" to="j_0" fromId="90" toId="62">
<BackEdge/>
<condition id="-1">
<or_exp><and_exp><literal name="icmp_ln393_1" val="1"/>
</and_exp></or_exp>
</condition>
</dataflow>
<dataflow id="269" from="br_ln304" to="j_0" fromId="91" toId="62">
<BackEdge/>
</dataflow>
<dataflow id="270" from="StgValue_195" to="curData_1_rec" fromId="195" toId="63">
<condition id="-1">
<or_exp><and_exp><literal name="icmp_ln302" val="1"/>
<literal name="icmp_ln303" val="1"/>
<literal name="icmp_ln303_1" val="0"/>
</and_exp></or_exp>
</condition>
</dataflow>
<dataflow id="271" from="br_ln304" to="curData_1_rec" fromId="59" toId="63">
</dataflow>
<dataflow id="272" from="add_ln310" to="curData_1_rec" fromId="89" toId="63">
<BackEdge/>
<condition id="-1">
<or_exp><and_exp><literal name="icmp_ln393_1" val="1"/>
</and_exp></or_exp>
</condition>
</dataflow>
<dataflow id="273" from="br_ln304" to="curData_1_rec" fromId="91" toId="63">
<BackEdge/>
</dataflow>
<dataflow id="274" from="j_0" to="icmp_ln304" fromId="62" toId="64">
</dataflow>
<dataflow id="276" from="StgValue_275" to="icmp_ln304" fromId="275" toId="64">
</dataflow>
<dataflow id="277" from="icmp_ln304" to="br_ln304" fromId="64" toId="65">
</dataflow>
<dataflow id="278" from="KeccakP1600_Permute_" to="call_ln305" fromId="216" toId="66">
</dataflow>
<dataflow id="279" from="instance_state" to="call_ln305" fromId="163" toId="66">
</dataflow>
<dataflow id="280" from="KeccakRhoOffsets" to="call_ln305" fromId="169" toId="66">
</dataflow>
<dataflow id="281" from="KeccakRoundConstants" to="call_ln305" fromId="170" toId="66">
</dataflow>
<dataflow id="282" from="dataByteLen_cast" to="zext_ln312" fromId="21" toId="67">
</dataflow>
<dataflow id="283" from="j_0" to="trunc_ln312" fromId="62" toId="68">
</dataflow>
<dataflow id="284" from="zext_ln312" to="sub_ln312" fromId="67" toId="69">
</dataflow>
<dataflow id="285" from="trunc_ln312" to="sub_ln312" fromId="68" toId="69">
</dataflow>
<dataflow id="286" from="sub_ln312" to="store_ln313" fromId="69" toId="70">
</dataflow>
<dataflow id="287" from="i_36" to="store_ln313" fromId="41" toId="70">
</dataflow>
<dataflow id="288" from="KeccakP1600_Permute_" to="call_ln305" fromId="216" toId="72">
</dataflow>
<dataflow id="289" from="instance_state" to="call_ln305" fromId="163" toId="72">
</dataflow>
<dataflow id="290" from="KeccakRhoOffsets" to="call_ln305" fromId="169" toId="72">
</dataflow>
<dataflow id="291" from="KeccakRoundConstants" to="call_ln305" fromId="170" toId="72">
</dataflow>
<dataflow id="292" from="loop_53" to="loop_0_i" fromId="76" toId="74">
<BackEdge/>
<condition id="-1">
<or_exp><and_exp></and_exp></or_exp>
</condition>
</dataflow>
<dataflow id="293" from="br_ln393" to="loop_0_i" fromId="96" toId="74">
<BackEdge/>
</dataflow>
<dataflow id="295" from="StgValue_294" to="loop_0_i" fromId="294" toId="74">
<condition id="-1">
<or_exp><and_exp></and_exp></or_exp>
</condition>
</dataflow>
<dataflow id="296" from="br_ln390" to="loop_0_i" fromId="73" toId="74">
</dataflow>
<dataflow id="297" from="loop_0_i" to="icmp_ln393_1" fromId="74" toId="75">
</dataflow>
<dataflow id="299" from="StgValue_298" to="icmp_ln393_1" fromId="298" toId="75">
</dataflow>
<dataflow id="300" from="loop_0_i" to="loop_53" fromId="74" toId="76">
</dataflow>
<dataflow id="301" from="StgValue_201" to="loop_53" fromId="201" toId="76">
</dataflow>
<dataflow id="303" from="_ssdm_op_SpecLoopTripCount" to="empty" fromId="302" toId="77">
</dataflow>
<dataflow id="304" from="StgValue_275" to="empty" fromId="275" toId="77">
</dataflow>
<dataflow id="305" from="StgValue_275" to="empty" fromId="275" toId="77">
</dataflow>
<dataflow id="306" from="StgValue_275" to="empty" fromId="275" toId="77">
</dataflow>
<dataflow id="307" from="icmp_ln393_1" to="br_ln393" fromId="75" toId="78">
</dataflow>
<dataflow id="308" from="loop_0_i" to="zext_ln394_1" fromId="74" toId="79">
</dataflow>
<dataflow id="309" from="loop_0_i" to="zext_ln394_15" fromId="74" toId="80">
</dataflow>
<dataflow id="310" from="instance_state" to="instance_state_addr_3" fromId="163" toId="81">
</dataflow>
<dataflow id="311" from="StgValue_195" to="instance_state_addr_3" fromId="195" toId="81">
</dataflow>
<dataflow id="312" from="zext_ln394_1" to="instance_state_addr_3" fromId="79" toId="81">
</dataflow>
<dataflow id="313" from="instance_state_addr_3" to="instance_state_load_3" fromId="81" toId="82">
</dataflow>
<dataflow id="314" from="curData_1_rec" to="trunc_ln304" fromId="63" toId="83">
</dataflow>
<dataflow id="315" from="zext_ln394_15" to="add_ln394_3" fromId="80" toId="84">
</dataflow>
<dataflow id="316" from="trunc_ln304" to="add_ln394_3" fromId="83" toId="84">
</dataflow>
<dataflow id="317" from="curData_0_idx" to="trunc_ln302_4" fromId="47" toId="85">
</dataflow>
<dataflow id="318" from="trunc_ln302_4" to="add_ln394_2" fromId="85" toId="86">
</dataflow>
<dataflow id="319" from="add_ln394_3" to="add_ln394_2" fromId="84" toId="86">
</dataflow>
<dataflow id="320" from="add_ln394_2" to="zext_ln394_16" fromId="86" toId="87">
</dataflow>
<dataflow id="321" from="select_ln394" to="add_ln394_11" fromId="23" toId="88">
</dataflow>
<dataflow id="322" from="zext_ln394_16" to="add_ln394_11" fromId="87" toId="88">
</dataflow>
<dataflow id="323" from="curData_1_rec" to="add_ln310" fromId="63" toId="89">
</dataflow>
<dataflow id="324" from="StgValue_275" to="add_ln310" fromId="275" toId="89">
</dataflow>
<dataflow id="325" from="j_0" to="j_18" fromId="62" toId="90">
</dataflow>
<dataflow id="327" from="StgValue_326" to="j_18" fromId="326" toId="90">
</dataflow>
<dataflow id="328" from="instance_state_addr_3" to="instance_state_load_3" fromId="81" toId="92">
</dataflow>
<dataflow id="329" from="add_ln394_11" to="sext_ln394_1" fromId="88" toId="93">
</dataflow>
<dataflow id="330" from="data_0" to="data_0_addr_1" fromId="166" toId="94">
</dataflow>
<dataflow id="331" from="StgValue_195" to="data_0_addr_1" fromId="195" toId="94">
</dataflow>
<dataflow id="332" from="sext_ln394_1" to="data_0_addr_1" fromId="93" toId="94">
</dataflow>
<dataflow id="333" from="instance_state_load_3" to="store_ln394" fromId="92" toId="95">
</dataflow>
<dataflow id="334" from="data_0_addr_1" to="store_ln394" fromId="94" toId="95">
</dataflow>
<dataflow id="335" from="KeccakP1600_Permute_" to="call_ln317" fromId="216" toId="97">
</dataflow>
<dataflow id="336" from="instance_state" to="call_ln317" fromId="163" toId="97">
</dataflow>
<dataflow id="337" from="KeccakRhoOffsets" to="call_ln317" fromId="169" toId="97">
</dataflow>
<dataflow id="338" from="KeccakRoundConstants" to="call_ln317" fromId="170" toId="97">
</dataflow>
<dataflow id="339" from="i_36_load" to="trunc_ln320" fromId="48" toId="99">
</dataflow>
<dataflow id="340" from="zext_ln320" to="partialBlock" fromId="43" toId="100">
</dataflow>
<dataflow id="341" from="trunc_ln320" to="partialBlock" fromId="99" toId="100">
</dataflow>
<dataflow id="342" from="StgValue_190" to="offset_assign_1" fromId="190" toId="101">
<condition id="-1">
<or_exp><and_exp><literal name="icmp_ln303" val="1"/>
</and_exp></or_exp>
</condition>
</dataflow>
<dataflow id="343" from="br_ln319" to="offset_assign_1" fromId="98" toId="101">
</dataflow>
<dataflow id="344" from="instance_byteIOIndex_1" to="offset_assign_1" fromId="46" toId="101">
<condition id="-1">
<or_exp><and_exp><literal name="icmp_ln302" val="1"/>
<literal name="icmp_ln303" val="0"/>
</and_exp></or_exp>
</condition>
</dataflow>
<dataflow id="345" from="br_ln303" to="offset_assign_1" fromId="52" toId="101">
</dataflow>
<dataflow id="346" from="offset_assign_1" to="add_ln321" fromId="101" toId="102">
</dataflow>
<dataflow id="347" from="partialBlock" to="add_ln321" fromId="100" toId="102">
</dataflow>
<dataflow id="348" from="add_ln321" to="icmp_ln321" fromId="102" toId="103">
</dataflow>
<dataflow id="349" from="StgValue_249" to="icmp_ln321" fromId="249" toId="103">
</dataflow>
<dataflow id="350" from="StgValue_249" to="partialBlock_17" fromId="249" toId="104">
</dataflow>
<dataflow id="351" from="offset_assign_1" to="partialBlock_17" fromId="101" toId="104">
</dataflow>
<dataflow id="352" from="icmp_ln321" to="partialBlock_18" fromId="103" toId="105">
</dataflow>
<dataflow id="353" from="partialBlock_17" to="partialBlock_18" fromId="104" toId="105">
</dataflow>
<dataflow id="354" from="partialBlock" to="partialBlock_18" fromId="100" toId="105">
</dataflow>
<dataflow id="355" from="partialBlock_18" to="zext_ln323" fromId="105" toId="106">
</dataflow>
<dataflow id="356" from="partialBlock_18" to="zext_ln323_4" fromId="105" toId="107">
</dataflow>
<dataflow id="357" from="i_36_load" to="i" fromId="48" toId="108">
</dataflow>
<dataflow id="358" from="zext_ln323_4" to="i" fromId="107" toId="108">
</dataflow>
<dataflow id="359" from="loop" to="loop_0_i1" fromId="112" toId="110">
<BackEdge/>
<condition id="-1">
<or_exp><and_exp></and_exp></or_exp>
</condition>
</dataflow>
<dataflow id="360" from="br_ln393" to="loop_0_i1" fromId="130" toId="110">
<BackEdge/>
</dataflow>
<dataflow id="361" from="StgValue_190" to="loop_0_i1" fromId="190" toId="110">
<condition id="-1">
<or_exp><and_exp></and_exp></or_exp>
</condition>
</dataflow>
<dataflow id="362" from="br_ln390" to="loop_0_i1" fromId="109" toId="110">
</dataflow>
<dataflow id="363" from="loop_0_i1" to="icmp_ln393" fromId="110" toId="111">
</dataflow>
<dataflow id="364" from="partialBlock_18" to="icmp_ln393" fromId="105" toId="111">
</dataflow>
<dataflow id="365" from="loop_0_i1" to="loop" fromId="110" toId="112">
</dataflow>
<dataflow id="366" from="StgValue_229" to="loop" fromId="229" toId="112">
</dataflow>
<dataflow id="367" from="icmp_ln393" to="br_ln393" fromId="111" toId="113">
</dataflow>
<dataflow id="368" from="offset_assign_1" to="add_ln394" fromId="101" toId="114">
</dataflow>
<dataflow id="369" from="loop_0_i1" to="add_ln394" fromId="110" toId="114">
</dataflow>
<dataflow id="370" from="add_ln394" to="zext_ln394" fromId="114" toId="115">
</dataflow>
<dataflow id="371" from="instance_state" to="instance_state_addr_2" fromId="163" toId="116">
</dataflow>
<dataflow id="372" from="StgValue_195" to="instance_state_addr_2" fromId="195" toId="116">
</dataflow>
<dataflow id="373" from="zext_ln394" to="instance_state_addr_2" fromId="115" toId="116">
</dataflow>
<dataflow id="374" from="instance_state_addr_2" to="instance_state_load_2" fromId="116" toId="117">
</dataflow>
<dataflow id="375" from="loop_0_i1" to="trunc_ln394" fromId="110" toId="118">
</dataflow>
<dataflow id="376" from="curData_0_idx" to="trunc_ln302" fromId="47" toId="119">
</dataflow>
<dataflow id="377" from="trunc_ln394" to="add_ln394_1" fromId="118" toId="120">
</dataflow>
<dataflow id="378" from="trunc_ln302" to="add_ln394_1" fromId="119" toId="120">
</dataflow>
<dataflow id="379" from="add_ln394_1" to="zext_ln394_14" fromId="120" toId="121">
</dataflow>
<dataflow id="380" from="select_ln394" to="add_ln394_10" fromId="23" toId="122">
</dataflow>
<dataflow id="381" from="zext_ln394_14" to="add_ln394_10" fromId="121" toId="122">
</dataflow>
<dataflow id="382" from="offset_assign_1" to="add_ln330" fromId="101" toId="123">
</dataflow>
<dataflow id="383" from="partialBlock_18" to="add_ln330" fromId="105" toId="123">
</dataflow>
<dataflow id="384" from="i" to="store_ln323" fromId="108" toId="124">
</dataflow>
<dataflow id="385" from="i_36" to="store_ln323" fromId="41" toId="124">
</dataflow>
<dataflow id="386" from="instance_state_addr_2" to="instance_state_load_2" fromId="116" toId="126">
</dataflow>
<dataflow id="387" from="add_ln394_10" to="sext_ln394" fromId="122" toId="127">
</dataflow>
<dataflow id="388" from="data_0" to="data_0_addr" fromId="166" toId="128">
</dataflow>
<dataflow id="389" from="StgValue_195" to="data_0_addr" fromId="195" toId="128">
</dataflow>
<dataflow id="390" from="sext_ln394" to="data_0_addr" fromId="127" toId="128">
</dataflow>
<dataflow id="391" from="instance_state_load_2" to="store_ln394" fromId="126" toId="129">
</dataflow>
<dataflow id="392" from="data_0_addr" to="store_ln394" fromId="128" toId="129">
</dataflow>
<dataflow id="393" from="add_ln330" to="instance_byteIOIndex_3" fromId="123" toId="131">
<condition id="-1">
<or_exp><and_exp><literal name="icmp_ln393" val="1"/>
</and_exp></or_exp>
</condition>
</dataflow>
<dataflow id="394" from="br_ln0" to="instance_byteIOIndex_3" fromId="125" toId="131">
</dataflow>
<dataflow id="395" from="StgValue_249" to="instance_byteIOIndex_3" fromId="249" toId="131">
<condition id="-1">
<or_exp><and_exp><literal name="icmp_ln304" val="1"/>
</and_exp></or_exp>
</condition>
</dataflow>
<dataflow id="396" from="br_ln313" to="instance_byteIOIndex_3" fromId="71" toId="131">
</dataflow>
<dataflow id="397" from="zext_ln323" to="curData_1_rec_pn" fromId="106" toId="132">
<condition id="-1">
<or_exp><and_exp><literal name="icmp_ln393" val="1"/>
</and_exp></or_exp>
</condition>
</dataflow>
<dataflow id="398" from="br_ln0" to="curData_1_rec_pn" fromId="125" toId="132">
</dataflow>
<dataflow id="399" from="curData_1_rec" to="curData_1_rec_pn" fromId="63" toId="132">
<condition id="-1">
<or_exp><and_exp><literal name="icmp_ln304" val="1"/>
</and_exp></or_exp>
</condition>
</dataflow>
<dataflow id="400" from="br_ln313" to="curData_1_rec_pn" fromId="71" toId="132">
</dataflow>
<dataflow id="401" from="curData_1_rec_pn" to="add_ln329" fromId="132" toId="133">
</dataflow>
<dataflow id="402" from="curData_0_idx" to="add_ln329" fromId="47" toId="133">
</dataflow>
<dataflow id="403" from="icmp_ln297" to="StgValue_1" fromId="24" toId="1">
</dataflow>
<dataflow id="404" from="icmp_ln297" to="StgValue_6" fromId="24" toId="6">
</dataflow>
<dataflow id="405" from="icmp_ln302" to="StgValue_7" fromId="49" toId="7">
</dataflow>
<dataflow id="406" from="icmp_ln303" to="StgValue_7" fromId="51" toId="7">
</dataflow>
<dataflow id="407" from="icmp_ln303_1" to="StgValue_7" fromId="55" toId="7">
</dataflow>
<dataflow id="408" from="icmp_ln304" to="StgValue_8" fromId="64" toId="8">
</dataflow>
<dataflow id="409" from="icmp_ln393_1" to="StgValue_10" fromId="75" toId="10">
</dataflow>
<dataflow id="410" from="icmp_ln303" to="StgValue_12" fromId="51" toId="12">
</dataflow>
<dataflow id="411" from="icmp_ln393" to="StgValue_14" fromId="111" toId="14">
</dataflow>
</dataflows>


</stg>
